MANIFEST.in
README.md
info.py
setup.py
delaunator/__init__.py
delaunator/delaunator.py
delaunator.egg-info/PKG-INFO
delaunator.egg-info/SOURCES.txt
delaunator.egg-info/dependency_links.txt
delaunator.egg-info/top_level.txt
delaunator/libdelaunator_src/__init__.py
delaunator/libdelaunator_src/commons.h
delaunator/libdelaunator_src/delaunator.cpp
delaunator/libdelaunator_src/delaunator.h
delaunator/libdelaunator_src/edge.cpp
delaunator/libdelaunator_src/edge.h
delaunator/libdelaunator_src/edge_iterators.h
delaunator/libdelaunator_src/face.cpp
delaunator/libdelaunator_src/face.h
delaunator/libdelaunator_src/face_iterators.h
delaunator/libdelaunator_src/geometry.cpp
delaunator/libdelaunator_src/geometry.h
delaunator/libdelaunator_src/inlines.h
delaunator/libdelaunator_src/iterators.h
delaunator/libdelaunator_src/iterators.i
delaunator/libdelaunator_src/libdelaunator.i
delaunator/libdelaunator_src/libdelaunator.py
delaunator/libdelaunator_src/main.cpp
delaunator/libdelaunator_src/main.h
delaunator/libdelaunator_src/meshGenerator.cpp
delaunator/libdelaunator_src/meshGenerator.h
delaunator/libdelaunator_src/python_trianguledObject.i
delaunator/libdelaunator_src/templates.h
delaunator/libdelaunator_src/triangulation.cpp
delaunator/libdelaunator_src/triangulation.h
delaunator/libdelaunator_src/utils.cpp
delaunator/libdelaunator_src/utils.h
delaunator/libdelaunator_src/vertex.cpp
delaunator/libdelaunator_src/vertex.h
delaunator/libdelaunator_src/vertexGroup.cpp
delaunator/libdelaunator_src/vertexGroup.h
delaunator/libdelaunator_src/vertex_iterators.h
delaunator/libdelaunator_src/virtualVertex.cpp
delaunator/libdelaunator_src/virtualVertex.h