Metadata-Version: 1.1
Name: delaunator
Version: 1.0.4
Summary: 2D Delaunay Triangulation in C++ with Python wrapper
Home-page: https://github.com/Aluriak/Delaunator
Author: aluriak
Author-email: lucas.bourneuf@laposte.net
License: UNKNOWN
Keywords: triangulation geometry delaunay wrapper
Platform: UNKNOWN
Classifier: License :: OSI Approved :: GNU General Public License (GPL)
Classifier: Natural Language :: English
Classifier: Operating System :: Unix
Classifier: Programming Language :: C
Classifier: Programming Language :: C++
Classifier: Programming Language :: Python :: 3
Classifier: Programming Language :: Python
Classifier: Topic :: Scientific/Engineering
Classifier: Topic :: Software Development :: Libraries :: Python Modules
